env_export_top.pth
env_export_top.py
env_export_top-0.0.dist-info/METADATA
env_export_top-0.0.dist-info/WHEEL
env_export_top-0.0.dist-info/top_level.txt
env_export_top-0.0.dist-info/RECORD
