Metadata-Version: 2.1
Name: env-export-top
Version: 0.0
Summary: ensure that $TOP is always exported
Home-page: https://github.com/bukzor/python-env-export-top
Author: Buck Evan
Author-email: buck.2019@gmail.com
License: MIT
Platform: UNKNOWN
Classifier: Programming Language :: Python :: 3.6
Classifier: License :: OSI Approved :: MIT License
